pyoctree/__init__.py
pyoctree/cOctree.cpp
pyoctree/cOctree.h
pyoctree/pyoctree.cp36-win_amd64.pyd
pyoctree/pyoctree.cpp
pyoctree/pyoctree.pyx
pyoctree/version.py
pyoctree/Examples/knot.stl
pyoctree/Examples/octree.vtu
pyoctree/Examples/pyoctree-intersection.ipynb
pyoctree/Examples/pyoctree-intro.ipynb
pyoctree/Examples/pyoctree-shadowcasting.ipynb
pyoctree/Examples/.ipynb_checkpoints/pyoctree-intersection-checkpoint.ipynb
pyoctree/Examples/.ipynb_checkpoints/pyoctree-intro-checkpoint.ipynb
pyoctree/Examples/.ipynb_checkpoints/pyoctree-shadowcasting-checkpoint.ipynb
pyoctree-0.2.10.dist-info/LICENSE.txt
pyoctree-0.2.10.dist-info/METADATA
pyoctree-0.2.10.dist-info/RECORD
pyoctree-0.2.10.dist-info/WHEEL
pyoctree-0.2.10.dist-info/top_level.txt
