Metadata-Version: 2.1
Name: pyoctree
Version: 0.2.10
Summary: Octree structure containing 3D triangular mesh model
Home-page: https://github.com/mhogg/pyoctree
Author: Michael Hogg
Author-email: michael.christopher.hogg@gmail.com
License: MIT license
Download-URL: https://github.com/mhogg/pyoctree/releases
Keywords: octree,triangle,mesh,python,cython,ray,tracing
Platform: UNKNOWN
Classifier: Development Status :: 4 - Beta
Classifier: Environment :: Other Environment
Classifier: License :: OSI Approved :: MIT License
Classifier: Operating System :: OS Independent
Classifier: Programming Language :: Python
Classifier: Programming Language :: Cython
Classifier: Programming Language :: C++
Classifier: Programming Language :: Python :: 2
Classifier: Programming Language :: Python :: 2.7
Classifier: Programming Language :: Python :: 3
Classifier: Programming Language :: Python :: 3.6
Requires-Dist: numpy
